VerdictCut/__init__.py
VerdictCut/find_fact.py
VerdictCut/find_justice.py
VerdictCut/find_laws.py
VerdictCut/find_maintext.py
VerdictCut/find_roles.py
VerdictCut/tool/__init__.py
VerdictCut/tool/find_name_law.py
VerdictCut/tool/get_units_list.py
VerdictCut/tool/normalize_position.py
VerdictCut-0.1.6.dist-info/LICENSE.txt
VerdictCut-0.1.6.dist-info/METADATA
VerdictCut-0.1.6.dist-info/WHEEL
VerdictCut-0.1.6.dist-info/top_level.txt
VerdictCut-0.1.6.dist-info/RECORD
