Metadata-Version: 2.1
Name: VerdictCut
Version: 0.1.6
Summary: cut the verdict into different part
Home-page: https://github.com/seanbbear/VerdictCut
Author: seanbbear
Author-email: k7489759@gmail.com
License: UNKNOWN
Platform: UNKNOWN
Classifier: Programming Language :: Python :: 3
Classifier: License :: OSI Approved :: MIT License
Classifier: Operating System :: OS Independent
Requires-Python: >=3.6
